LICENSE
README.md
setup.py
karas/__init__.py
karas/box.py
karas/chain.py
karas/elements.py
karas/event.py
karas/exceptions.py
karas/messages.py
karas/permission.py
karas/sender.py
karas/util/Listener.py
karas/util/Logger.py
karas/util/__init__.py
karas/util/network.py
karas/util/sync.py
karas_py.egg-info/PKG-INFO
karas_py.egg-info/SOURCES.txt
karas_py.egg-info/dependency_links.txt
karas_py.egg-info/requires.txt
karas_py.egg-info/top_level.txt