Metadata-Version: 2.1
Name: karas-py
Version: 0.2.11
Summary: 一个基于mirai-api-http的高性能qq消息处理框架
Home-page: https://github.com/ShiroDoMain/Karas
Author: ShiroDoMain
Author-email: b1808107177@gmail.com
License: GNU Affero General Public License v3.0
Keywords: qqbot async
Classifier: Programming Language :: Python :: 3.7
Classifier: Programming Language :: Python :: 3.8
Classifier: Programming Language :: Python :: 3.9
Classifier: Programming Language :: Python :: 3.10
License-File: LICENSE
